LICENSE.txt
README.md
setup.cfg
setup.py
topsis_aryamank_102003099/__init__.py
topsis_aryamank_102003099/topsis_102003099.py
topsis_aryamank_102003099.egg-info/PKG-INFO
topsis_aryamank_102003099.egg-info/SOURCES.txt
topsis_aryamank_102003099.egg-info/dependency_links.txt
topsis_aryamank_102003099.egg-info/requires.txt
topsis_aryamank_102003099.egg-info/top_level.txt